google/cloud/translate/__init__.py
google/cloud/translate/gapic_version.py
google/cloud/translate/py.typed
google/cloud/translate_v2/__init__.py
google/cloud/translate_v2/_http.py
google/cloud/translate_v2/client.py
google/cloud/translate_v3/__init__.py
google/cloud/translate_v3/gapic_metadata.json
google/cloud/translate_v3/gapic_version.py
google/cloud/translate_v3/py.typed
google/cloud/translate_v3/services/__init__.py
google/cloud/translate_v3/services/translation_service/__init__.py
google/cloud/translate_v3/services/translation_service/async_client.py
google/cloud/translate_v3/services/translation_service/client.py
google/cloud/translate_v3/services/translation_service/pagers.py
google/cloud/translate_v3/services/translation_service/transports/__init__.py
google/cloud/translate_v3/services/translation_service/transports/base.py
google/cloud/translate_v3/services/translation_service/transports/grpc.py
google/cloud/translate_v3/services/translation_service/transports/grpc_asyncio.py
google/cloud/translate_v3/services/translation_service/transports/rest.py
google/cloud/translate_v3/services/translation_service/transports/rest_base.py
google/cloud/translate_v3/types/__init__.py
google/cloud/translate_v3/types/adaptive_mt.py
google/cloud/translate_v3/types/automl_translation.py
google/cloud/translate_v3/types/common.py
google/cloud/translate_v3/types/translation_service.py
google/cloud/translate_v3beta1/__init__.py
google/cloud/translate_v3beta1/gapic_metadata.json
google/cloud/translate_v3beta1/gapic_version.py
google/cloud/translate_v3beta1/py.typed
google/cloud/translate_v3beta1/services/__init__.py
google/cloud/translate_v3beta1/services/translation_service/__init__.py
google/cloud/translate_v3beta1/services/translation_service/async_client.py
google/cloud/translate_v3beta1/services/translation_service/client.py
google/cloud/translate_v3beta1/services/translation_service/pagers.py
google_cloud_translate-3.21.0.dist-info/licenses/LICENSE
google_cloud_translate-3.21.0.dist-info/METADATA
google_cloud_translate-3.21.0.dist-info/WHEEL
google_cloud_translate-3.21.0.dist-info/top_level.txt
google_cloud_translate-3.21.0.dist-info/RECORD
